{"version":"2.1","services":{"yapi":{"image":"mrjin/yapi:latest","container_name":"yapi","environment":["VERSION=1.8.1","LOG_PATH=/tmp/yapi.log","HOME=/home","PORT=3000","ADMIN_EMAIL=jiahua.fu@shuyun.com","DB_SERVER=mongo","DB_NAME=yapi","DB_PORT=27017"],"restart":"always","ports":["127.0.0.1:3000:3000"],"depends_on":["mongo"],"entrypoint":"bash /wait-for-it.sh mongo:27017 -- entrypoint.sh","networks":["yapi-net"]},"mongo":{"image":"mongo","container_name":"mongo","restart":"always","ports":["127.0.0.1:27017:27017"],"volumes":["~/data/yapi/mongodb:/data/db"],"networks":["yapi-net"]}},"networks":{"yapi-net":{"external":true}}}